pan_os_cli/__init__.py
pan_os_cli/client.py
pan_os_cli/commands/__init__.py
pan_os_cli/commands/objects.py
pan_os_cli/config.py
pan_os_cli/main.py
pan_os_cli/models/objects.py
pan_os_cli/utils.py
pan_os_cli-0.1.0.dist-info/METADATA
pan_os_cli-0.1.0.dist-info/WHEEL
pan_os_cli-0.1.0.dist-info/entry_points.txt
pan_os_cli-0.1.0.dist-info/RECORD
