Metadata-Version: 2.3
Name: pan-os-cli
Version: 0.1.0
Summary: CLI tool for managing PAN-OS configurations with multi-threading support
Author: Calvin Remsburg
Author-email: cremsburg@protonmail.com
Requires-Python: >=3.10,<3.13
Classifier: Programming Language :: Python :: 3
Classifier: Programming Language :: Python :: 3.10
Classifier: Programming Language :: Python :: 3.11
Classifier: Programming Language :: Python :: 3.12
Requires-Dist: concurrent-log-handler (>=0.9.24,<0.10.0)
Requires-Dist: dynaconf (>=3.2.10,<4.0.0)
Requires-Dist: pan-os-python (>=1.12.1,<2.0.0)
Requires-Dist: pydantic (>=2.11.1,<3.0.0)
Requires-Dist: pyyaml (>=6.0.1,<7.0.0)
Requires-Dist: requests (>=2.32.3,<3.0.0)
Requires-Dist: rich (>=13.6.0,<14.0.0)
Requires-Dist: setuptools (>=78.1.0,<79.0.0)
Requires-Dist: typer[all] (>=0.15.2,<0.16.0)
